namemaker/__init__.py
namemaker/name data/England towns.txt
namemaker/name data/Greek mythology.txt
namemaker/name data/PA towns.txt
namemaker/name data/female first names.txt
namemaker/name data/last names.txt
namemaker/name data/male first names.txt
namemaker-1.1.2.dist-info/LICENSE.txt
namemaker-1.1.2.dist-info/METADATA
namemaker-1.1.2.dist-info/WHEEL
namemaker-1.1.2.dist-info/top_level.txt
namemaker-1.1.2.dist-info/RECORD
