Metadata-Version: 2.1
Name: namemaker
Version: 1.1.2
Summary: A random name generator using Markov chains.
Home-page: https://github.com/Rickmsd/namemaker
Author: Rick Moyer
Author-email: rickmoyer.sd@gmail.com
License: UNKNOWN
Platform: UNKNOWN
Classifier: Programming Language :: Python :: 3
Classifier: License :: OSI Approved :: MIT License
Classifier: Operating System :: OS Independent
Classifier: Topic :: Games/Entertainment
Requires-Python: >=3.6
License-File: LICENSE.txt
